datar/__init__.py
datar/all.py
datar/apis/__init__.py
datar/apis/base.py
datar/apis/dplyr.py
datar/apis/forcats.py
datar/apis/misc.py
datar/apis/tibble.py
datar/apis/tidyr.py
datar/base.py
datar/core/__init__.py
datar/core/defaults.py
datar/core/load_plugins.py
datar/core/names.py
datar/core/operator.py
datar/core/options.py
datar/core/plugin.py
datar/core/utils.py
datar/core/verb_env.py
datar/data/__init__.py
datar/data/airlines.csv.gz
datar/data/airports.csv.gz
datar/data/airquality.csv.gz
datar/data/anscombe.csv.gz
datar/data/band_instruments.csv.gz
datar/data/band_instruments2.csv.gz
datar/data/band_members.csv.gz
datar/data/billboard.csv.gz
datar/data/chickweight.csv.gz
datar/data/cms_patient_care.csv.gz
datar/data/cms_patient_experience.csv.gz
datar/data/construction.csv.gz
datar/data/diamonds.csv.gz
datar/data/economics.csv.gz
datar/data/economics_long.csv.gz
datar/data/faithful.csv.gz
datar/data/faithfuld.csv.gz
datar/data/fish_encounters.csv.gz
datar/data/flights.csv.gz
datar/data/gss_cat.csv.gz
datar/data/household.csv.gz
datar/data/iris.csv.gz
datar/data/luv_colours.csv.gz
datar/data/metadata.py
datar/data/midwest.csv.gz
datar/data/mpg.csv.gz
datar/data/msleep.csv.gz
datar/data/mtcars.csv.gz
datar/data/planes.csv.gz
datar/data/population.csv.gz
datar/data/presidential.csv.gz
datar/data/relig_income.csv.gz
datar/data/seals.csv.gz
datar/data/smiths.csv.gz
datar/data/starwars.csv.gz
datar/data/state_abb.csv.gz
datar/data/state_division.csv.gz
datar/data/state_region.csv.gz
datar/data/storms.csv.gz
datar/data/table1.csv.gz
datar/data/table2.csv.gz
datar/data/table3.csv.gz
datar/data/table4a.csv.gz
datar/data/table4b.csv.gz
datar/data/table5.csv.gz
datar/data/toothgrowth.csv.gz
datar/data/txhousing.csv.gz
datar/data/us_rent_income.csv.gz
datar/data/warpbreaks.csv.gz
datar/data/weather.csv.gz
datar/data/who.csv.gz
datar/data/who2.csv.gz
datar/data/world_bank_pop.csv.gz
datar/datasets.py
datar/dplyr.py
datar/forcats.py
datar/misc.py
datar/tibble.py
datar-0.15.14.dist-info/METADATA
datar-0.15.14.dist-info/WHEEL
datar-0.15.14.dist-info/licenses/LICENSE
datar-0.15.14.dist-info/RECORD
