Metadata-Version: 2.4
Name: datar
Version: 0.15.14
Summary: A Grammar of Data Manipulation in python
License: MIT
License-File: LICENSE
Author: pwwang
Author-email: pwwang@pwwang.com
Requires-Python: >=3.9,<4.0
Classifier: License :: OSI Approved :: MIT License
Classifier: Programming Language :: Python :: 3
Classifier: Programming Language :: Python :: 3.9
Classifier: Programming Language :: Python :: 3.10
Classifier: Programming Language :: Python :: 3.11
Classifier: Programming Language :: Python :: 3.12
Classifier: Programming Language :: Python :: 3.13
Classifier: Programming Language :: Python :: 3.14
Provides-Extra: arrow
Provides-Extra: numpy
Provides-Extra: pandas
Requires-Dist: datar-arrow (>=0.2,<0.3) ; extra == "arrow"
Requires-Dist: datar-numpy (>=0.3.4,<0.4.0) ; extra == "numpy"
Requires-Dist: datar-pandas (>=0.6,<0.7) ; extra == "pandas"
Requires-Dist: pipda (>=0.13.1,<0.14.0)
Requires-Dist: python-simpleconf[toml] (>=0.8,<0.9)
Requires-Dist: simplug (>=0.5,<0.6)
Project-URL: Homepage, https://github.com/pwwang/datar
Project-URL: Repository, https://github.com/pwwang/datar
